examples/__init__.py
flexlate/__init__.py
flexlate/add_mode.py
flexlate/adder.py
flexlate/bootstrapper.py
flexlate/branch_update.py
flexlate/checker.py
flexlate/cli.py
flexlate/cli_utils.py
flexlate/config.py
flexlate/config_manager.py
flexlate/constants.py
flexlate/error_handler.py
flexlate/exc.py
flexlate/ext_git.py
flexlate/get_version.py
flexlate/logger.py
flexlate/main.py
flexlate/merger.py
flexlate/path_ops.py
flexlate/pusher.py
flexlate/remover.py
flexlate/styles.py
flexlate/syncer.py
flexlate/temp_path.py
flexlate/template_data.py
flexlate/template_path.py
flexlate/types.py
flexlate/user_config_manager.py
flexlate/finder/__init__.py
flexlate/finder/multi.py
flexlate/finder/specific/__init__.py
flexlate/finder/specific/base.py
flexlate/finder/specific/cookiecutter.py
flexlate/finder/specific/copier.py
flexlate/finder/specific/git.py
flexlate/render/__init__.py
flexlate/render/multi.py
flexlate/render/renderable.py
flexlate/render/specific/__init__.py
flexlate/render/specific/base.py
flexlate/render/specific/cookiecutter.py
flexlate/render/specific/copier.py
flexlate/template/__init__.py
flexlate/template/base.py
flexlate/template/cookiecutter.py
flexlate/template/copier.py
flexlate/template/hashing.py
flexlate/template/types.py
flexlate/template_config/__init__.py
flexlate/template_config/base.py
flexlate/template_config/cookiecutter.py
flexlate/template_config/copier.py
flexlate/transactions/__init__.py
flexlate/transactions/transaction.py
flexlate/transactions/undoer.py
flexlate/update/__init__.py
flexlate/update/main.py
flexlate/update/template.py
tests/__init__.py
tests/config.py
tests/conftest.py
tests/confutils.py
tests/dirutils.py
tests/ext_click.py
tests/ext_subprocess.py
tests/fileutils.py
tests/fs_checks.py
tests/gen_configs.py
tests/gitutils.py
tests/test_add.py
tests/test_bootstrapper.py
tests/test_checker.py
tests/test_config.py
tests/test_finder.py
tests/test_merge.py
tests/test_placeholder.py
tests/test_pusher.py
tests/test_remove.py
flexlate-0.14.7.dist-info/LICENSE.md
flexlate-0.14.7.dist-info/METADATA
flexlate-0.14.7.dist-info/WHEEL
flexlate-0.14.7.dist-info/entry_points.txt
flexlate-0.14.7.dist-info/top_level.txt
flexlate-0.14.7.dist-info/RECORD
