Metadata-Version: 2.1
Name: flexlate
Version: 0.14.7
Summary: A composable, maintainable system for managing templates
Home-page: https://github.com/nickderobertis/flexlate
Author: Nick DeRobertis
Author-email: whoopnip@gmail.com
License: MIT
Project-URL: Code, https://github.com/nickderobertis/flexlate
Project-URL: Documentation, https://nickderobertis.github.io/flexlate
Classifier: Development Status :: 3 - Alpha
Classifier: Intended Audience :: Developers
Classifier: Programming Language :: Python :: 3.6
Classifier: Programming Language :: Python :: 3.7
License-File: LICENSE.md
Requires-Dist: py-app-conf
Requires-Dist: cookiecutter
Requires-Dist: gitpython
Requires-Dist: click (<8.1)
Requires-Dist: typer
Requires-Dist: rich
Requires-Dist: markupsafe (<2.1)
Requires-Dist: copier (==5.*)
